vttformatter/__init__.py
vttformatter/vttformatter.py
vttformatter-2.11.dist-info/LICENSE
vttformatter-2.11.dist-info/METADATA
vttformatter-2.11.dist-info/WHEEL
vttformatter-2.11.dist-info/top_level.txt
vttformatter-2.11.dist-info/RECORD
