Metadata-Version: 2.1
Name: vttformatter
Version: 2.11
Summary: WEBVTT to text converter
Home-page: https://github.com/georgiewellock/VTT_formatter
Author: Georgina L. Wellock
Author-email: g.l.wellock@bath.ac.uk
License: MIT
Download-URL: https://github.com/georgiewellock/VTT_formatter/archive/2.11.tar.gz
Platform: UNKNOWN
Requires-Dist: numpy
